typedb_protocol/__init__.py
typedb_protocol/cluster/__init__.py
typedb_protocol/cluster/cluster_database_pb2.py
typedb_protocol/cluster/cluster_database_pb2_grpc.py
typedb_protocol/cluster/cluster_server_pb2.py
typedb_protocol/cluster/cluster_server_pb2_grpc.py
typedb_protocol/cluster/cluster_service_pb2.py
typedb_protocol/cluster/cluster_service_pb2_grpc.py
typedb_protocol/cluster/cluster_user_pb2.py
typedb_protocol/cluster/cluster_user_pb2_grpc.py
typedb_protocol/common/__init__.py
typedb_protocol/common/answer_pb2.py
typedb_protocol/common/answer_pb2_grpc.py
typedb_protocol/common/concept_pb2.py
typedb_protocol/common/concept_pb2_grpc.py
typedb_protocol/common/connection_pb2.py
typedb_protocol/common/connection_pb2_grpc.py
typedb_protocol/common/logic_pb2.py
typedb_protocol/common/logic_pb2_grpc.py
typedb_protocol/common/options_pb2.py
typedb_protocol/common/options_pb2_grpc.py
typedb_protocol/common/query_pb2.py
typedb_protocol/common/query_pb2_grpc.py
typedb_protocol/common/session_pb2.py
typedb_protocol/common/session_pb2_grpc.py
typedb_protocol/common/transaction_pb2.py
typedb_protocol/common/transaction_pb2_grpc.py
typedb_protocol/common/version_pb2.py
typedb_protocol/common/version_pb2_grpc.py
typedb_protocol/core/__init__.py
typedb_protocol/core/core_database_pb2.py
typedb_protocol/core/core_database_pb2_grpc.py
typedb_protocol/core/core_service_pb2.py
typedb_protocol/core/core_service_pb2_grpc.py
typedb_protocol-2.18.1.dist-info/METADATA
typedb_protocol-2.18.1.dist-info/WHEEL
typedb_protocol-2.18.1.dist-info/top_level.txt
typedb_protocol-2.18.1.dist-info/RECORD
