Metadata-Version: 2.1
Name: typedb-protocol
Version: 2.18.1
Summary: TypeDB Protocol
Home-page: https://github.com/vaticle/typedb-protocol/
Author: Vaticle
Author-email: community@vaticle.com
License: AGPL-3.0
Keywords: typedb typeql type-system strongly-typed database knowledge-base
Classifier: Programming Language :: Python
Classifier: Programming Language :: Python :: 3
Classifier: Programming Language :: Python :: 3.6
Classifier: Programming Language :: Python :: 3.7
Classifier: Programming Language :: Python :: 3.8
Classifier: Programming Language :: Python :: 3.9
Classifier: License :: OSI Approved :: GNU Affero General Public License v3 or later (AGPLv3+)
Classifier: Operating System :: OS Independent
Classifier: Intended Audience :: Developers
Classifier: Intended Audience :: Science/Research
Classifier: Environment :: Console
Classifier: Topic :: Database :: Front-Ends
Requires-Python: >3.6.0
